pelican_gemini_capsule.py
pelican_gemini_capsule-0.4.0.dist-info/licenses/COPYING
pelican_gemini_capsule-0.4.0.dist-info/WHEEL
pelican_gemini_capsule-0.4.0.dist-info/METADATA
pelican_gemini_capsule-0.4.0.dist-info/RECORD
