Metadata-Version: 2.4
Name: pelican-gemini-capsule
Version: 0.4.0
Summary: Pelican plugin to generate Gemini capsules
Keywords: pelican,gemini,capsule,gemtext,gmi
Author: Fabien LOISON
Requires-Python: >=3.9
License-Expression: GPL-3.0-or-later
License-File: COPYING
Requires-Dist: rst2gemtext
Requires-Dist: nox ; extra == "dev"
Requires-Dist: flit ; extra == "dev"
Requires-Dist: black ; extra == "dev"
Requires-Dist: flake8 ; extra == "dev"
Requires-Dist: flake8-pyproject ; extra == "dev"
Requires-Dist: validate-pyproject ; extra == "dev"
Project-URL: changelog, https://github.com/flozz/pelican-gemini-capsule?tab=readme-ov-file#changelog
Project-URL: chat, https://discord.gg/P77sWhuSs4
Project-URL: documentation, https://github.com/flozz/pelican-gemini-capsule/blob/master/README.rst
Project-URL: donate, https://github.com/flozz/pelican-gemini-capsule#support-this-project
Project-URL: issues, https://github.com/flozz/pelican-gemini-capsule/issues
Project-URL: source, https://github.com/flozz/pelican-gemini-capsule
Provides-Extra: dev
